filesystemserver/__init__.py
filesystemserver/filesystemserver.py
filesystemserver/data/plugin/fss/favicon.png
filesystemserver/data/plugin/fss/fss.js
filesystemserver/data/plugin/fss/browser/app.js
filesystemserver/data/plugin/fss/browser/index.html
filesystemserver/data/plugin/fss/browser/style.css
filesystemserver-0.0.7.dist-info/METADATA
filesystemserver-0.0.7.dist-info/WHEEL
filesystemserver-0.0.7.dist-info/entry_points.txt
filesystemserver-0.0.7.dist-info/licenses/LICENSE
filesystemserver-0.0.7.dist-info/RECORD
