Metadata-Version: 2.3
Name: filesystemserver
Version: 0.0.7
Summary: File System Server
Project-URL: Homepage, https://github.com/nicholashaydensmith/filesystemserver
Project-URL: Issues, https://github.com/nicholashaydensmith/filesystemserver/issues
Author-email: Nicholas Smith <thesmithdynasty@gmail.com>
License-File: LICENSE
Classifier: Intended Audience :: Developers
Classifier: License :: OSI Approved :: MIT License
Classifier: Operating System :: OS Independent
Classifier: Programming Language :: Python :: 3
Classifier: Topic :: Utilities
Requires-Python: >=3.8
Requires-Dist: tomli; python_version < '3.11'
